streamlit_lchart_card/__init__.py
streamlit_lchart_card/frontend/build/asset-manifest.json
streamlit_lchart_card/frontend/build/bootstrap.min.css
streamlit_lchart_card/frontend/build/index.html
streamlit_lchart_card/frontend/build/precache-manifest.3afa9a0b8c470b6609b95f8791286030.js
streamlit_lchart_card/frontend/build/service-worker.js
streamlit_lchart_card/frontend/build/static/js/2.e2d5a64e.chunk.js
streamlit_lchart_card/frontend/build/static/js/2.e2d5a64e.chunk.js.LICENSE.txt
streamlit_lchart_card/frontend/build/static/js/2.e2d5a64e.chunk.js.map
streamlit_lchart_card/frontend/build/static/js/main.371af992.chunk.js
streamlit_lchart_card/frontend/build/static/js/main.371af992.chunk.js.map
streamlit_lchart_card/frontend/build/static/js/runtime-main.44d30fc2.js
streamlit_lchart_card/frontend/build/static/js/runtime-main.44d30fc2.js.map
streamlit_lchart_card-1.0.1.dist-info/LICENSE
streamlit_lchart_card-1.0.1.dist-info/METADATA
streamlit_lchart_card-1.0.1.dist-info/WHEEL
streamlit_lchart_card-1.0.1.dist-info/top_level.txt
streamlit_lchart_card-1.0.1.dist-info/RECORD
