Metadata-Version: 2.1
Name: streamlit-lchart-card
Version: 1.0.1
Summary: Chart card component
Home-page: https://github.com/victorC97/streamlit_graphic_card
Author: victorC97
Author-email: victor.cour@telecomnancy.net
License: UNKNOWN
Platform: UNKNOWN
Requires-Python: >=3.6
Requires-Dist: streamlit (>=0.63)
